{ "verbs" :
    [
        {
            "id": 0,
            "group": "mixed",
            "infinitive": "denken",
            "present": "denkt",
            "past": "dachte",
            "past_participle": "gedacht",
            "perfect_aux": "haben",
            "conjunctive2": "dächte",
            "imperative": "denk(e)",
            "ablaut": "aa"
        },
        {
            "id": 1,
            "group": "mixed",
            "infinitive": "haben",
            "present": "hat",
            "past": "hatte",
            "past_participle": "gehabt",
            "perfect_aux": "haben",
            "conjunctive2": "hätte",
            "imperative": "hab(e)",
            "ablaut": "aa"
        },
        {
            "id": 2,
            "group": "mixed",
            "infinitive": "kennen",
            "present": "kennt",
            "past": "kannte",
            "past_participle": "gekannt",
            "perfect_aux": "haben",
            "conjunctive2": "kennte",
            "imperative": "kenn(e)",
            "ablaut": "aa"
        },
        {
            "id": 3,
            "group": "mixed",
            "infinitive": "nennen",
            "present": "nennt",
            "past": "nannte",
            "past_participle": "genannt",
            "perfect_aux": "haben",
            "conjunctive2": "nennte",
            "imperative": "nenn(e)",
            "ablaut": "aa"
        },
        {
            "id": 4,
            "group": "mixed",
            "infinitive": "rennen",
            "present": "rennt",
            "past": "rannte",
            "past_participle": "gerannt",
            "perfect_aux": "sein",
            "conjunctive2": "rennte",
            "imperative": "renn(e)",
            "ablaut": "aa"
        },
        {
            "id": 5,
            "group": "mixed",
            "infinitive": "brennen",
            "present": "brennt",
            "past": "brannte",
            "past_participle": "gebrannt",
            "perfect_aux": "haben",
            "conjunctive2": "brennte",
            "imperative": "brenn(e)",
            "ablaut": "aa"
        },
        {
            "id": 6,
            "group": "mixed",
            "infinitive": "bringen",
            "present": "bringt",
            "past": "brachte",
            "past_participle": "gebracht",
            "perfect_aux": "haben",
            "conjunctive2": "brächte",
            "imperative": "bring(e)",
            "ablaut": "aa"
        },
        {
            "id": 7,
            "group": "mixed",
            "infinitive": "senden",
            "present": "sendet",
            "past": "sandte",
            "past2": "sendete",
            "past_participle": "gesandt",
            "past_participle2": "gesendet",
            "perfect_aux": "haben",
            "conjunctive2": "sendete",
            "imperative": "send(e)",
            "ablaut": "aa"
        },
        {
            "id": 8,
            "group": "strong",
            "infinitive": "stehen",
            "present": "steht",
            "past": "stand",
            "past_participle": "gestanden",
            "perfect_aux": "haben",
            "perfect_aux2": "sein",
            "conjunctive2": "stünde",
            "conjunctive2_2": "stände",
            "imperative": "steh(e)",
            "ablaut": "aa"
        },
        {
            "id": 9,
            "group": "strong",
            "infinitive": "tun",
            "present": "tut",
            "past": "tat",
            "past_participle": "getan",
            "perfect_aux": "haben",
            "conjunctive2": "täte",
            "imperative": "tu(e)",
            "ablaut": "aa"
        },
        {
            "id": 10,
            "group": "mixed",
            "infinitive": "wenden",
            "present": "wendet",
            "past": "wandte",
            "past2": "wendete",
            "past_participle": "gewandt",
            "past_participle2": "gewendet",
            "perfect_aux": "haben",
            "perfect_aux2": "sein",
            "conjunctive2": "wendete",
            "imperative": "wend(e)",
            "ablaut": "aa"
        },
        {
            "id": 11,
            "group": "strong",
            "infinitive": "bitten",
            "present": "bittet",
            "past": "bat",
            "past_participle": "gebeten",
            "perfect_aux": "haben",
            "conjunctive2": "bäte",
            "imperative": "bitt(e)",
            "ablaut": "ae"
        },
        {
            "id": 12,
            "group": "strong",
            "infinitive": "essen",
            "present": "isst",
            "past": "aß",
            "past_participle": "gegessen",
            "perfect_aux": "haben",
            "conjunctive2": "äße",
            "imperative": "iss",
            "ablaut": "ae"
        },
        {
            "id": 13,
            "group": "strong",
            "infinitive": "fressen",
            "present": "frisst",
            "past": "fraß",
            "past_participle": "gefressen",
            "perfect_aux": "haben",
            "conjunctive2": "fräße",
            "imperative": "friss",
            "ablaut": "ae"
        },
        {
            "id": 14,
            "group": "strong",
            "infinitive": "geben",
            "present": "gibt",
            "past": "gab",
            "past_participle": "gegeben",
            "perfect_aux": "haben",
            "conjunctive2": "gäbe",
            "imperative": "gib",
            "ablaut": "ae"
        },
        {
            "id": 15,
            "group": "strong",
            "infinitive": "geschehen",
            "present": "geschieht",
            "past": "geschah",
            "past_participle": "geschehen",
            "perfect_aux": "sein",
            "conjunctive2": "geschähe",
            "imperative": "geschieh(e)",
            "ablaut": "ae"
        },
        {
            "id": 16,
            "group": "strong",
            "infinitive": "lesen",
            "present": "liest",
            "past": "las",
            "past_participle": "gelesen",
            "perfect_aux": "haben",
            "conjunctive2": "läse",
            "imperative": "lies",
            "ablaut": "ae"
        },
        {
            "id": 17,
            "group": "strong",
            "infinitive": "liegen",
            "present": "liegt",
            "past": "lag",
            "past_participle": "gelegen",
            "perfect_aux": "haben",
            "perfect_aux2": "sein",
            "conjunctive2": "läge",
            "imperative": "lieg(e)",
            "ablaut": "ae"
        },
        {
            "id": 18,
            "group": "strong",
            "infinitive": "messen",
            "present": "misst",
            "past": "maß",
            "past_participle": "gemessen",
            "perfect_aux": "haben",
            "conjunctive2": "mäße",
            "imperative": "miss",
            "ablaut": "ae"
        },
        {
            "id": 19,
            "group": "strong",
            "infinitive": "sehen",
            "present": "sieht",
            "past": "sah",
            "past_participle": "gesehen",
            "perfect_aux": "haben",
            "conjunctive2": "sähe",
            "imperative": "sieh",
            "ablaut": "ae"
        },
        {
            "id": 20,
            "group": "strong",
            "infinitive": "sein",
            "present": "ist",
            "past": "war",
            "past_participle": "gewesen",
            "perfect_aux": "sein",
            "conjunctive2": "wäre",
            "imperative": "sei",
            "ablaut": "ae"
        },
        {
            "id": 21,
            "group": "strong",
            "infinitive": "sitzen",
            "present": "sitzt",
            "past": "saß",
            "past_participle": "gesessen",
            "perfect_aux": "hat",
            "perfect_aux2": "sein",
            "conjunctive2": "säße",
            "imperative": "sitz(e)",
            "ablaut": "ae"
        },
        {
            "id": 22,
            "group": "strong",
            "infinitive": "treten",
            "present": "tritt",
            "past": "trat",
            "past_participle": "getreten",
            "perfect_aux": "haben",
            "perfect_aux2": "sein",
            "conjunctive2": "träte",
            "imperative": "tritt",
            "ablaut": "ae"
        },
        {
            "id": 23,
            "group": "strong",
            "infinitive": "vergessen",
            "present": "vergisst",
            "past": "vergaß",
            "past_participle": "vergessen",
            "perfect_aux": "haben",
            "conjunctive2": "vergäße",
            "imperative": "vergiss",
            "ablaut": "ae"
        },
        {
            "id": 24,
            "group": "strong",
            "infinitive": "befehlen",
            "present": "befiehlt",
            "past": "befahl",
            "past_participle": "befohlen",
            "perfect_aux": "haben",
            "conjunctive2": "befähle",
            "conjunctive2_2": "beföhle",
            "imperative": "befiehl",
            "ablaut": "ao"
        },
        {
            "id": 25,
            "group": "strong",
            "infinitive": "beginnen",
            "present": "beginnt",
            "past": "begann",
            "past_participle": "begonnen",
            "perfect_aux": "haben",
            "conjunctive2": "begänne",
            "conjunctive2_2": "begönne",
            "imperative": "beginn(e)",
            "ablaut": "ao"
        },
        {
            "id": 26,
            "group": "strong",
            "infinitive": "brechen",
            "present": "bricht",
            "past": "brach",
            "past_participle": "gebrochen",
            "perfect_aux": "haben",
            "conjunctive2": "bräche",
            "imperative": "brich",
            "ablaut": "ao"
        },
        {
            "id": 27,
            "group": "strong",
            "infinitive": "empfehlen",
            "present": "empfiehlt",
            "past": "empfahl",
            "past_participle": "empfohlen",
            "perfect_aux": "haben",
            "conjunctive2": "empfähle",
            "conjunctive2_2": "empföhle",
            "imperative": "empfiehl",
            "ablaut": "ao"
        },
        {
            "id": 28,
            "group": "strong",
            "infinitive": "erschrecken",
            "present": "erschrickt",
            "past": "erschrak",
            "past_participle": "erschrocken",
            "perfect_aux": "sein",
            "perfect_aux2": "haben",
            "conjunctive2": "erschräke",
            "imperative": "erschrick",
            "ablaut": "ao"
        },
        {
            "id": 29,
            "group": "strong",
            "infinitive": "gelten",
            "present": "gilt",
            "past": "galt",
            "past_participle": "gegolten",
            "perfect_aux": "haben",
            "conjunctive2": "gälte",
            "conjunctive2_2": "gölte",
            "imperative": "gilt",
            "ablaut": "ao"
        },
        {
            "id": 30,
            "group": "strong",
            "infinitive": "gewinnen",
            "present": "gewinnt",
            "past": "gewann",
            "past_participle": "gewonnen",
            "perfect_aux": "haben",
            "conjunctive2": "gewänne",
            "conjunctive2_2": "gewönne",
            "imperative": "gewinn(e)",
            "ablaut": "ao"
        },
        {
            "id": 31,
            "group": "strong",
            "infinitive": "helfen",
            "present": "hilft",
            "past": "half",
            "past_participle": "geholfen",
            "perfect_aux": "haben",
            "conjunctive2": "hälf",
            "conjunctive2_2": "hülfe",
            "imperative": "hilf",
            "ablaut": "ao"
        },
        {
            "id": 32,
            "group": "strong",
            "infinitive": "kommen",
            "present": "kommt",
            "past": "kam",
            "past_participle": "gekommen",
            "perfect_aux": "sein",
            "conjunctive2": "käme",
            "imperative": "komm(e)",
            "ablaut": "ao"
        },
        {
            "id": 33,
            "group": "strong",
            "infinitive": "nehmen",
            "present": "nimmt",
            "past": "nahm",
            "past_participle": "genommen",
            "perfect_aux": "haben",
            "conjunctive2": "nähme",
            "imperative": "nimm",
            "ablaut": "ao"
        },
        {
            "id": 34,
            "group": "strong",
            "infinitive": "schwimmen",
            "present": "schwimmen",
            "past": "schwamm",
            "past_participle": "geschwommen",
            "perfect_aux": "sein",
            "perfect_aux2": "haben",
            "conjunctive2": "schwämme",
            "conjunctive2_2": "schwömme",
            "imperative": "schwimm",
            "ablaut": "ao"
        },
        {
            "id": 35,
            "group": "strong",
            "infinitive": "sprechen",
            "present": "spricht",
            "past": "sprach",
            "past_participle": "gesprochen",
            "perfect_aux": "haben",
            "conjunctive2": "spräche",
            "imperative": "sprich",
            "ablaut": "ao"
        },
        {
            "id": 36,
            "group": "strong",
            "infinitive": "stechen",
            "present": "sticht",
            "past": "stach",
            "past_participle": "gestochen",
            "perfect_aux": "haben",
            "conjunctive2": "stäche",
            "imperative": "stich",
            "ablaut": "ao"
        },
        {
            "id": 37,
            "group": "strong",
            "infinitive": "stehlen",
            "present": "stiehlt",
            "past": "stahl",
            "past_participle": "gestohlen",
            "perfect_aux": "haben",
            "conjunctive2": "stähle",
            "conjunctive2_2": "stöhle",
            "imperative": "stiehl",
            "ablaut": "ao"
        },
        {
            "id": 38,
            "group": "strong",
            "infinitive": "sterben",
            "present": "stirbt",
            "past": "starb",
            "past_participle": "gestorben",
            "perfect_aux": "sein",
            "conjunctive2": "stürbe",
            "imperative": "stirb",
            "ablaut": "ao"
        },
        {
            "id": 39,
            "group": "strong",
            "infinitive": "treffen",
            "present": "trifft",
            "past": "traf",
            "past_participle": "getroffen",
            "perfect_aux": "haben",
            "conjunctive2": "träfe",
            "imperative": "triff",
            "ablaut": "ao"
        },
        {
            "id": 40,
            "group": "strong",
            "infinitive": "verderben",
            "present": "verdirbt",
            "past": "verdarb",
            "past_participle": "verdorben",
            "perfect_aux": "sein",
            "conjunctive2": "verdürbe",
            "imperative": "verdirb",
            "ablaut": "ao"
        },
        {
            "id": 41,
            "group": "strong",
            "infinitive": "werben",
            "present": "wirbt",
            "past": "warb",
            "past_participle": "geworben",
            "perfect_aux": "haben",
            "conjunctive2": "würbe",
            "imperative": "wirb",
            "ablaut": "ao"
        },
        {
            "id": 42,
            "group": "strong",
            "infinitive": "werfen",
            "present": "wirft",
            "past": "warf",
            "past_participle": "geworfen",
            "perfect_aux": "haben",
            "conjunctive2": "würfe",
            "imperative": "wirf",
            "ablaut": "ao"
        },
        {
            "id": 43,
            "group": "strong",
            "infinitive": "binden",
            "present": "bindet",
            "past": "band",
            "past_participle": "gebunden",
            "perfect_aux": "haben",
            "conjunctive2": "bände",
            "imperative": "bind(e)",
            "ablaut": "au"
        },
        {
            "id": 44,
            "group": "strong",
            "infinitive": "eindringen",
            "present": "dringt ein",
            "past": "drang ein",
            "past_participle": "eingedrungen",
            "perfect_aux": "sein",
            "conjunctive2": "dränge ein",
            "imperative": "dring(e)",
            "ablaut": "au"
        },
        {
            "id": 45,
            "group": "strong",
            "infinitive": "empfinden",
            "present": "empfindet",
            "past": "empfand",
            "past_participle": "empfunden",
            "perfect_aux": "haben",
            "conjunctive2": "empfände",
            "imperative": "empfind(e)",
            "ablaut": "au"
        },
        {
            "id": 46,
            "group": "strong",
            "infinitive": "finden",
            "present": "findet",
            "past": "fand",
            "past_participle": "gefunden",
            "perfect_aux": "haben",
            "conjunctive2": "fände",
            "imperative": "find(e)",
            "ablaut": "au"
        },
        {
            "id": 47,
            "group": "strong",
            "infinitive": "gelingen",
            "present": "gelingt",
            "past": "gelang",
            "past_participle": "gelungen",
            "perfect_aux": "sein",
            "conjunctive2": "gelänge",
            "imperative": "geling(e)",
            "ablaut": "au"
        },
        {
            "id": 48,
            "group": "strong",
            "infinitive": "klingen",
            "present": "klingt",
            "past": "klang",
            "past_participle": "geklungen",
            "perfect_aux": "haben",
            "conjunctive2": "klänge",
            "imperative": "kling(e)",
            "ablaut": "au"
        },
        {
            "id": 49,
            "group": "strong",
            "infinitive": "singen",
            "present": "singt",
            "past": "sang",
            "past_participle": "gesungen",
            "perfect_aux": "haben",
            "conjunctive2": "sänge",
            "imperative": "sing(e)",
            "ablaut": "au"
        },
        {
            "id": 50,
            "group": "strong",
            "infinitive": "sinken",
            "present": "sinkt",
            "past": "sank",
            "past_participle": "gesunken",
            "perfect_aux": "sein",
            "conjunctive2": "sänke",
            "imperative": "sink(e)",
            "ablaut": "au"
        },
        {
            "id": 51,
            "group": "strong",
            "infinitive": "springen",
            "present": "springt",
            "past": "sprang",
            "past_participle": "gesprungen",
            "perfect_aux": "sein",
            "conjunctive2": "spränge",
            "imperative": "spring(e)",
            "ablaut": "au"
        },
        {
            "id": 52,
            "group": "strong",
            "infinitive": "stinken",
            "present": "stinkt",
            "past": "stank",
            "past_participle": "gestunken",
            "perfect_aux": "haben",
            "conjunctive2": "stänke",
            "imperative": "stink(e)",
            "ablaut": "au"
        },
        {
            "id": 53,
            "group": "strong",
            "infinitive": "trinken",
            "present": "trinkt",
            "past": "trank",
            "past_participle": "getrunken",
            "perfect_aux": "haben",
            "conjunctive2": "tränke",
            "imperative": "trink(e)",
            "ablaut": "au"
        },
        {
            "id": 54,
            "group": "strong",
            "infinitive": "verschwinden",
            "present": "veschwindet",
            "past": "verschwand",
            "past_participle": "verschwunden",
            "perfect_aux": "sein",
            "conjunctive2": "sänke",
            "imperative": "sink(e)",
            "ablaut": "au"
        },
        {
            "id": 55,
            "group": "strong",
            "infinitive": "zwingen",
            "present": "zwingt",
            "past": "zwang",
            "past_participle": "gezwungen",
            "perfect_aux": "haben",
            "conjunctive2": "zwänge",
            "imperative": "zwing(e)",
            "ablaut": "au"
        },
        {
            "id": 56,
            "group": "strong",
            "infinitive": "blasen",
            "present": "bläst",
            "past": "blies",
            "past_participle": "geblasen",
            "perfect_aux": "haben",
            "conjunctive2": "bliese",
            "imperative": "blas(e)",
            "ablaut": "ia"
        },
        {
            "id": 57,
            "group": "strong",
            "infinitive": "braten",
            "present": "brät",
            "past": "briet",
            "past_participle": "gebraten",
            "perfect_aux": "haben",
            "conjunctive2": "briete",
            "imperative": "brat(e)",
            "ablaut": "ia"
        },
        {
            "id": 58,
            "group": "strong",
            "infinitive": "empfangen",
            "present": "empfängt",
            "past": "empfing",
            "past_participle": "empfangen",
            "perfect_aux": "haben",
            "conjunctive2": "empfinge",
            "imperative": "empfang(e)",
            "ablaut": "ia"
        },
        {
            "id": 59,
            "group": "strong",
            "infinitive": "fallen",
            "present": "fällt",
            "past": "fiel",
            "past_participle": "gefallen",
            "perfect_aux": "sein",
            "conjunctive2": "fiele",
            "imperative": "fall(e)",
            "ablaut": "ia"
        },
        {
            "id": 60,
            "group": "strong",
            "infinitive": "fangen",
            "present": "fängt",
            "past": "fing",
            "past_participle": "gefangen",
            "perfect_aux": "haben",
            "conjunctive2": "finge",
            "imperative": "fang(e)",
            "ablaut": "ia"
        },
        {
            "id": 61,
            "group": "strong",
            "infinitive": "gehen",
            "present": "geht",
            "past": "ging",
            "past_participle": "gegangen",
            "perfect_aux": "sein",
            "conjunctive2": "ginge",
            "imperative": "geh(e)",
            "ablaut": "ia"
        },
        {
            "id": 62,
            "group": "strong",
            "infinitive": "geraten",
            "present": "gerät",
            "past": "geriet",
            "past_participle": "geraten",
            "perfect_aux": "sein",
            "conjunctive2": "geriete",
            "imperative": "gerat(e)",
            "ablaut": "ia"
        },
        {
            "id": 63,
            "group": "strong",
            "infinitive": "halten",
            "present": "hält",
            "past": "hielt",
            "past_participle": "gehalten",
            "perfect_aux": "haben",
            "conjunctive2": "hielte",
            "imperative": "halt(e)",
            "ablaut": "ia"
        },
        {
            "id": 64,
            "group": "strong",
            "infinitive": "hängen",
            "present": "hängt",
            "past": "hing",
            "past_participle": "gehangen",
            "perfect_aux": "haben",
            "perfect_aux2": "sein",
            "conjunctive2": "hinge",
            "imperative": "häng(e)",
            "ablaut": "ia"
        },
        {
            "id": 65,
            "group": "strong",
            "infinitive": "lassen",
            "present": "lässt",
            "past": "ließ",
            "past_participle": "gelassen",
            "past_participle2": "lassen",
            "perfect_aux": "haben",
            "conjunctive2": "ließe",
            "imperative": "lass(e)",
            "ablaut": "ia"
        },
        {
            "id": 66,
            "group": "strong",
            "infinitive": "laufen",
            "present": "läuft",
            "past": "lief",
            "past_participle": "gelaufen",
            "perfect_aux": "ist",
            "conjunctive2": "liefe",
            "imperative": "lauf(e)",
            "ablaut": "ia"
        },
        {
            "id": 67,
            "group": "strong",
            "infinitive": "raten",
            "present": "rät",
            "past": "riet",
            "past_participle": "geraten",
            "perfect_aux": "haben",
            "conjunctive2": "riete",
            "imperative": "rat(e)",
            "ablaut": "ia"
        },
        {
            "id": 68,
            "group": "strong",
            "infinitive": "schlafen",
            "present": "schläft",
            "past": "schlief",
            "past_participle": "geschlafen",
            "perfect_aux": "haben",
            "conjunctive2": "schliefe",
            "imperative": "schlaf(e)",
            "ablaut": "ia"
        },
        {
            "id": 69,
            "group": "strong",
            "infinitive": "heißen",
            "present": "heißt",
            "past": "hieß",
            "past_participle": "geheißen",
            "perfect_aux": "haben",
            "conjunctive2": "hieße",
            "imperative": "heiß(e)",
            "ablaut": "iei"
        },
        {
            "id": 70,
            "group": "strong",
            "infinitive": "beißen",
            "present": "beißt",
            "past": "biss",
            "past_participle": "gebissen",
            "perfect_aux": "haben",
            "conjunctive2": "bisse",
            "imperative": "beiß(e)",
            "ablaut": "ii"
        },
        {
            "id": 71,
            "group": "strong",
            "infinitive": "scheißen",
            "present": "scheißt",
            "past": "schiss",
            "past_participle": "geschissen",
            "perfect_aux": "haben",
            "conjunctive2": "schisse",
            "imperative": "scheiß(e)",
            "ablaut": "ii"
        },
        {
            "id": 72,
            "group": "strong",
            "infinitive": "schmeißen",
            "present": "schmeißen",
            "past": "schmiss",
            "past_participle": "geschmissen",
            "perfect_aux": "haben",
            "conjunctive2": "schmisse",
            "imperative": "schmeiß(e)",
            "ablaut": "ii"
        },
        {
            "id": 73,
            "group": "strong",
            "infinitive": "bleiben",
            "present": "bleibt",
            "past": "blieb",
            "past_participle": "geblieben",
            "perfect_aux": "sein",
            "conjunctive2": "bliebe",
            "imperative": "bleib(e)",
            "ablaut": "ii"
        },
        {
            "id": 74,
            "group": "strong",
            "infinitive": "vergleichen",
            "present": "vergleicht",
            "past": "verglich",
            "past_participle": "verglichen",
            "perfect_aux": "haben",
            "conjunctive2": "vergliche",
            "imperative": "vergleich(e)",
            "ablaut": "ii"
        },
        {
            "id": 75,
            "group": "strong",
            "infinitive": "gleiten",
            "present": "gleitet",
            "past": "glitt",
            "past_participle": "geglitten",
            "perfect_aux": "sein",
            "conjunctive2": "glitte",
            "imperative": "gleit(e)",
            "ablaut": "ii"
        },
        {
            "id": 76,
            "group": "strong",
            "infinitive": "greifen",
            "present": "greift",
            "past": "griff",
            "past_participle": "gegriffen",
            "perfect_aux": "haben",
            "conjunctive2": "griffe",
            "imperative": "greif(e)",
            "ablaut": "ii"
        },
        {
            "id": 77,
            "group": "strong",
            "infinitive": "leiden",
            "present": "leidet",
            "past": "litt",
            "past_participle": "gelitten",
            "perfect_aux": "haben",
            "conjunctive2": "litte",
            "imperative": "leid(e)",
            "ablaut": "ii"
        },
        {
            "id": 78,
            "group": "strong",
            "infinitive": "leihen",
            "present": "leiht",
            "past": "lieh",
            "past_participle": "geliehen",
            "perfect_aux": "haben",
            "conjunctive2": "liehe",
            "imperative": "leih(e)",
            "ablaut": "ii"
        },
        {
            "id": 79,
            "group": "strong",
            "infinitive": "meiden",
            "present": "meidet",
            "past": "mied",
            "past_participle": "gemieden",
            "perfect_aux": "haben",
            "conjunctive2": "miede",
            "imperative": "meid(e)",
            "ablaut": "ii"
        },
        {
            "id": 80,
            "group": "strong",
            "infinitive": "pfeifen",
            "present": "pfeift",
            "past": "pfiff",
            "past_participle": "gepfiffen",
            "perfect_aux": "haben",
            "conjunctive2": "pfiffe",
            "imperative": "pfeif(e)",
            "ablaut": "ii"
        },
        {
            "id": 81,
            "group": "strong",
            "infinitive": "reiben",
            "present": "reibt",
            "past": "rieb",
            "past_participle": "gerieben",
            "perfect_aux": "haben",
            "conjunctive2": "riebe",
            "imperative": "reib(e)",
            "ablaut": "ii"
        },
        {
            "id": 82,
            "group": "strong",
            "infinitive": "reißen",
            "present": "reißt",
            "past": "riss",
            "past_participle": "gerissen",
            "perfect_aux": "haben",
            "perfect_aux2": "sein",
            "conjunctive2": "risse",
            "imperative": "reiß(e)",
            "ablaut": "ii"
        },
        {
            "id": 83,
            "group": "strong",
            "infinitive": "reiten",
            "present": "reitet",
            "past": "ritt",
            "past_participle": "geritten",
            "perfect_aux": "haben",
            "perfect_aux2": "sein",
            "conjunctive2": "ritte",
            "imperative": "reit(e)",
            "ablaut": "ii"
        },
        {
            "id": 84,
            "group": "strong",
            "infinitive": "scheinen",
            "present": "scheint",
            "past": "schien",
            "past_participle": "geschienen",
            "perfect_aux": "haben",
            "conjunctive2": "riebe",
            "imperative": "reib(e)",
            "ablaut": "ii"
        },
        {
            "id": 85,
            "group": "strong",
            "infinitive": "schleichen",
            "present": "schleicht",
            "past": "schlich",
            "past_participle": "geschlichen",
            "perfect_aux": "sein",
            "conjunctive2": "schliche",
            "imperative": "schleich(e)",
            "ablaut": "ii"
        },
        {
            "id": 86,
            "group": "strong",
            "infinitive": "schneiden",
            "present": "schneidet",
            "past": "schnitt",
            "past_participle": "geschnitten",
            "perfect_aux": "haben",
            "conjunctive2": "schnitte",
            "imperative": "schneid(e)",
            "ablaut": "ii"
        },
        {
            "id": 87,
            "group": "strong",
            "infinitive": "schreiben",
            "present": "schreibt",
            "past": "schrieb",
            "past_participle": "geschrieben",
            "perfect_aux": "haben",
            "conjunctive2": "schriebe",
            "imperative": "schreib(e)",
            "ablaut": "ii"
        },
        {
            "id": 88,
            "group": "strong",
            "infinitive": "schreien",
            "present": "schreit",
            "past": "schrie",
            "past_participle": "geschrien",
            "perfect_aux": "haben",
            "conjunctive2": "schrie",
            "imperative": "schrei(e)",
            "ablaut": "ii"
        },
        {
            "id": 89,
            "group": "strong",
            "infinitive": "schweigen",
            "present": "schweigt",
            "past": "schwieg",
            "past_participle": "geschwiegen",
            "perfect_aux": "haben",
            "conjunctive2": "schwiege",
            "imperative": "schweig(e)",
            "ablaut": "ii"
        },
        {
            "id": 90,
            "group": "strong",
            "infinitive": "steigen",
            "present": "steigt",
            "past": "stieg",
            "past_participle": "gestiegen",
            "perfect_aux": "sein",
            "conjunctive2": "stiege",
            "imperative": "steig(e)",
            "ablaut": "ii"
        },
        {
            "id": 91,
            "group": "strong",
            "infinitive": "streichen",
            "present": "streicht",
            "past": "strich",
            "past_participle": "gestrichen",
            "perfect_aux": "haben",
            "conjunctive2": "striche",
            "imperative": "streich(e)",
            "ablaut": "ii"
        },
        {
            "id": 92,
            "group": "strong",
            "infinitive": "streiten",
            "present": "streitet",
            "past": "stritt",
            "past_participle": "gestritten",
            "perfect_aux": "haben",
            "conjunctive2": "stritte",
            "imperative": "streit(e)",
            "ablaut": "ii"
        },
        {
            "id": 93,
            "group": "strong",
            "infinitive": "treiben",
            "present": "treibt",
            "past": "trieb",
            "past_participle": "getrieben",
            "perfect_aux": "haben",
            "conjunctive2": "triebe",
            "imperative": "treib(e)",
            "ablaut": "ii"
        },
        {
            "id": 94,
            "group": "strong",
            "infinitive": "verzeihen",
            "present": "verzeiht",
            "past": "verzieh",
            "past_participle": "verziehen",
            "perfect_aux": "haben",
            "conjunctive2": "verziehe",
            "imperative": "verzeih(e)",
            "ablaut": "ii"
        },
        {
            "id": 95,
            "group": "strong",
            "infinitive": "ausweichen",
            "present": "weicht aus",
            "past": "wich aus",
            "past_participle": "ausgewichen",
            "perfect_aux": "sein",
            "conjunctive2": "wiche aus",
            "imperative": "weich(e) aus",
            "ablaut": "ii"
        },
        {
            "id": 96,
            "group": "strong",
            "infinitive": "hinweisen",
            "present": "weist hin",
            "past": "wies hin",
            "past_participle": "hingewiesen",
            "perfect_aux": "haben",
            "conjunctive2": "wiese hin",
            "imperative": "weis(e) hin",
            "ablaut": "ii"
        },
        {
            "id": 97,
            "group": "strong",
            "infinitive": "stoßen",
            "present": "stößt",
            "past": "stieß",
            "past_participle": "gestoßen",
            "perfect_aux": "haben",
            "perfect_aux2": "sein",
            "conjunctive2": "stieße",
            "imperative": "stoß(e)",
            "ablaut": "io"
        },
        {
            "id": 98,
            "group": "strong",
            "infinitive": "rufen",
            "present": "ruft",
            "past": "rief",
            "past_participle": "gerufen",
            "perfect_aux": "haben",
            "conjunctive2": "riefe",
            "imperative": "ruf(e)",
            "ablaut": "iu"
        },
        {
            "id": 99,
            "group": "strong",
            "infinitive": "betrügen",
            "present": "betrügt",
            "past": "betrog",
            "past_participle": "betrogen",
            "perfect_aux": "haben",
            "conjunctive2": "betröge",
            "imperative": "betrüg(e)",
            "ablaut": "oo"
        },
        {
            "id": 100,
            "group": "strong",
            "infinitive": "bewegen",
            "present": "bewegt",
            "past": "bewog",
            "past_participle": "bewogen",
            "perfect_aux": "haben",
            "conjunctive2": "bewöge",
            "imperative": "beweg(e)",
            "ablaut": "oo"
        },
        {
            "id": 101,
            "group": "strong",
            "infinitive": "biegen",
            "present": "biegt",
            "past": "bog",
            "past_participle": "gebogen",
            "perfect_aux": "haben",
            "conjunctive2": "böge",
            "imperative": "bieg(e)",
            "ablaut": "oo"
        },
        {
            "id": 102,
            "group": "strong",
            "infinitive": "bieten",
            "present": "bietet",
            "past": "bot",
            "past_participle": "geboten",
            "perfect_aux": "haben",
            "conjunctive2": "böte",
            "imperative": "biet(e)",
            "ablaut": "oo"
        },
        {
            "id": 103,
            "group": "strong",
            "infinitive": "erlöschen",
            "present": "erlischt",
            "past": "erlosch",
            "past_participle": "erloschen",
            "perfect_aux": "sein",
            "conjunctive2": "erlösche",
            "imperative": "erlisch(e)",
            "ablaut": "oo"
        },
        {
            "id": 104,
            "group": "strong",
            "infinitive": "erwägen",
            "present": "erwägt",
            "past": "erwog",
            "past_participle": "betrogen",
            "perfect_aux": "haben",
            "conjunctive2": "betröge",
            "imperative": "betrüg(e)",
            "ablaut": "oo"
        },
        {
            "id": 105,
            "group": "strong",
            "infinitive": "erwägen",
            "present": "erwägt",
            "past": "erwog",
            "past_participle": "erwogen",
            "perfect_aux": "haben",
            "conjunctive2": "erwöge",
            "imperative": "erwieg(e)",
            "ablaut": "oo"
        },
        {
            "id": 106,
            "group": "strong",
            "infinitive": "fliegen",
            "present": "fliegt",
            "past": "flog",
            "past_participle": "geflogen",
            "perfect_aux": "sein",
            "perfect_aux2": "haben",
            "conjunctive2": "flöge",
            "imperative": "flieg(e)",
            "ablaut": "oo"
        },
        {
            "id": 107,
            "group": "strong",
            "infinitive": "fliehen",
            "present": "flieht",
            "past": "floh",
            "past_participle": "geflohen",
            "perfect_aux": "sein",
            "conjunctive2": "flöhe",
            "imperative": "flieh(e)",
            "ablaut": "oo"
        },
        {
            "id": 108,
            "group": "strong",
            "infinitive": "fließen",
            "present": "fließt",
            "past": "floss",
            "past_participle": "geflossen",
            "perfect_aux": "sein",
            "conjunctive2": "flösse",
            "imperative": "fließ(e)",
            "ablaut": "oo"
        },
        {
            "id": 109,
            "group": "strong",
            "infinitive": "frieren",
            "present": "friert",
            "past": "fror",
            "past_participle": "gefroren",
            "perfect_aux": "haben",
            "conjunctive2": "fröre",
            "imperative": "frier(e)",
            "ablaut": "oo"
        },
        {
            "id": 110,
            "group": "strong",
            "infinitive": "genießen",
            "present": "genießt",
            "past": "genoss",
            "past_participle": "genossen",
            "perfect_aux": "haben",
            "conjunctive2": "genösse",
            "imperative": "genieß(e)",
            "ablaut": "oo"
        },
        {
            "id": 111,
            "group": "strong",
            "infinitive": "gießen",
            "present": "gießt",
            "past": "goss",
            "past_participle": "gegossen",
            "perfect_aux": "haben",
            "conjunctive2": "gösse",
            "imperative": "gieß(e)",
            "ablaut": "oo"
        },
        {
            "id": 112,
            "group": "strong",
            "infinitive": "heben",
            "present": "hebt",
            "past": "hob",
            "past_participle": "gehoben",
            "perfect_aux": "haben",
            "conjunctive2": "höbe",
            "imperative": "heb(e)",
            "ablaut": "oo"
        },
        {
            "id": 113,
            "group": "preterite_present",
            "infinitive": "können",
            "present": "kann",
            "past": "konnte",
            "past_participle": "gekonnt",
            "past_participle2": "können",
            "perfect_aux": "haben",
            "conjunctive2": "könnte",
            "imperative": "kann",
            "ablaut": "oo"
        },
        {
            "id": 114,
            "group": "strong",
            "infinitive": "kriechen",
            "present": "kriecht",
            "past": "kroch",
            "past_participle": "gekrochen",
            "perfect_aux": "sein",
            "conjunctive2": "kröche",
            "imperative": "kriech(e)",
            "ablaut": "oo"
        },
        {
            "id": 115,
            "group": "strong",
            "infinitive": "lügen",
            "present": "lügt",
            "past": "log",
            "past_participle": "gelogen",
            "perfect_aux": "haben",
            "conjunctive2": "löge",
            "imperative": "lüg(e)",
            "ablaut": "oo"
        },
        {
            "id": 116,
            "group": "preterite_present",
            "infinitive": "mögen",
            "present": "mag",
            "past": "mochte",
            "past_participle": "gemocht",
            "perfect_aux": "haben",
            "conjunctive2": "möchte",
            "imperative": "mag",
            "ablaut": "oo"
        },
        {
            "id": 117,
            "group": "strong",
            "infinitive": "riechen",
            "present": "riecht",
            "past": "roch",
            "past_participle": "gerochen",
            "perfect_aux": "haben",
            "conjunctive2": "röche",
            "imperative": "riech(e)",
            "ablaut": "oo"
        },
        {
            "id": 118,
            "group": "strong",
            "infinitive": "schieben",
            "present": "schiebt",
            "past": "schob",
            "past_participle": "geschoben",
            "perfect_aux": "haben",
            "conjunctive2": "schöbe",
            "imperative": "schieb(e)",
            "ablaut": "oo"
        },
        {
            "id": 119,
            "group": "strong",
            "infinitive": "schießen",
            "present": "schießt",
            "past": "schoss",
            "past_participle": "geschossen",
            "perfect_aux": "haben",
            "conjunctive2": "schösse",
            "imperative": "schieß(e)",
            "ablaut": "oo"
        },
        {
            "id": 120,
            "group": "strong",
            "infinitive": "schließen",
            "present": "schließt",
            "past": "schloss",
            "past_participle": "geschlossen",
            "perfect_aux": "haben",
            "conjunctive2": "schlösse",
            "imperative": "schließ(e)",
            "ablaut": "oo"
        },
        {
            "id": 121,
            "group": "strong",
            "infinitive": "schmelzen",
            "present": "schmilzt",
            "past": "schmolz",
            "past_participle": "geschmolzen",
            "perfect_aux": "sein",
            "perfect_aux2": "haben",
            "conjunctive2": "schmölze",
            "imperative": "schmilz(e)",
            "ablaut": "oo"
        },
        {
            "id": 122,
            "group": "strong",
            "infinitive": "schwellen",
            "present": "schwillt",
            "past": "schwoll",
            "past_participle": "geschwollen",
            "perfect_aux": "sein",
            "conjunctive2": "schwölle",
            "imperative": "schwill(e)",
            "ablaut": "oo"
        },
        {
            "id": 123,
            "group": "strong",
            "infinitive": "schwören",
            "present": "schwört",
            "past": "schwor",
            "past_participle": "geschworen",
            "perfect_aux": "haben",
            "conjunctive2": "schwöre",
            "conjunctive2_2": "schwüre",
            "imperative": "schwör(e)",
            "ablaut": "oo"
        },
        {
            "id": 124,
            "group": "strong",
            "infinitive": "verlieren",
            "present": "verliert",
            "past": "verlor",
            "past_participle": "verloren",
            "perfect_aux": "haben",
            "conjunctive2": "verlöre",
            "imperative": "verlier(e)",
            "ablaut": "oo"
        },
        {
            "id": 125,
            "group": "strong",
            "infinitive": "wiegen",
            "present": "wiegt",
            "past": "wog",
            "past_participle": "gewogen",
            "perfect_aux": "haben",
            "conjunctive2": "wöge",
            "imperative": "wieg(e)",
            "ablaut": "oo"
        },
        {
            "id": 126,
            "group": "strong",
            "infinitive": "ziehen",
            "present": "zieht",
            "past": "zog",
            "past_participle": "gezogen",
            "perfect_aux": "haben",
            "perfect_aux2": "sein",
            "conjunctive2": "zöge",
            "imperative": "zieh(e)",
            "ablaut": "oo"
        },
        {
            "id": 127,
            "group": "strong",
            "infinitive": "backen",
            "present": "backt(bäckt)",
            "past": "backte(buk)",
            "past_participle": "gebacken",
            "perfect_aux": "haben",
            "conjunctive2": "backte",
            "conjunctive2_2": "büke",
            "imperative": "back(e)",
            "ablaut": "ua"
        },
        {
            "id": 128,
            "group": "strong",
            "infinitive": "fahren",
            "present": "fährt",
            "past": "fuhr",
            "past_participle": "gefahren",
            "perfect_aux": "sein",
            "perfect_aux2": "haben",
            "conjunctive2": "führe",
            "imperative": "fahr(e)",
            "ablaut": "ua"
        },
        {
            "id": 129,
            "group": "strong",
            "infinitive": "graben",
            "present": "gräbt",
            "past": "grub",
            "past_participle": "gegraben",
            "perfect_aux": "haben",
            "conjunctive2": "grübe",
            "imperative": "grab(e)",
            "ablaut": "ua"
        },
        {
            "id": 130,
            "group": "strong",
            "infinitive": "laden",
            "present": "lädt",
            "past": "lud",
            "past_participle": "geladen",
            "perfect_aux": "haben",
            "conjunctive2": "lüde",
            "imperative": "lad(e)",
            "ablaut": "ua"
        },
        {
            "id": 131,
            "group": "strong",
            "infinitive": "schaffen",
            "present": "schafft",
            "past": "schuf",
            "past_participle": "geschaffen",
            "perfect_aux": "haben",
            "conjunctive2": "schüfe",
            "imperative": "schaff(e)",
            "ablaut": "ua"
        },
        {
            "id": 132,
            "group": "strong",
            "infinitive": "schlagen",
            "present": "schlägt",
            "past": "schlug",
            "past_participle": "geschlagen",
            "perfect_aux": "haben",
            "conjunctive2": "schlüge",
            "imperative": "schlag(e)",
            "ablaut": "ua"
        },
        {
            "id": 133,
            "group": "strong",
            "infinitive": "tragen",
            "present": "trägt",
            "past": "trug",
            "past_participle": "getragen",
            "perfect_aux": "haben",
            "conjunctive2": "trüge",
            "imperative": "trag(e)",
            "ablaut": "ua"
        },
        {
            "id": 134,
            "group": "strong",
            "infinitive": "wachsen",
            "present": "wächst",
            "past": "wuchs",
            "past_participle": "gewachsen",
            "perfect_aux": "sein",
            "conjunctive2": "wüchse",
            "imperative": "wachs(e)",
            "ablaut": "ua"
        },
        {
            "id": 135,
            "group": "strong",
            "infinitive": "waschen",
            "present": "wäscht",
            "past": "wusch",
            "past_participle": "gewaschen",
            "perfect_aux": "haben",
            "conjunctive2": "wüsche",
            "imperative": "wasch(e)",
            "ablaut": "ua"
        },
        {
            "id": 136,
            "group": "strong",
            "infinitive": "werden",
            "present": "wird",
            "past": "wurde",
            "past_participle": "geworden",
            "past_participle2": "worden",
            "perfect_aux": "sein",
            "conjunctive2": "würde",
            "imperative": "werd(e)",
            "ablaut": "uo"
        },
        {
            "id": 137,
            "group": "preterite_present",
            "infinitive": "dürfen",
            "present": "darf",
            "past": "durfte",
            "past_participle": "gedurft",
            "past_participle2": "dürfen",
            "perfect_aux": "haben",
            "conjunctive2": "dürfte",
            "imperative": "darf",
            "ablaut": "uu"
        },
        {
            "id": 138,
            "group": "preterite_present",
            "infinitive": "müssen",
            "present": "muss",
            "past": "musste",
            "past_participle": "gemusst",
            "past_participle2": "müssen",
            "perfect_aux": "haben",
            "conjunctive2": "müsste",
            "imperative": "muss",
            "ablaut": "uu"
        },
        {
            "id": 139,
            "group": "preterite_present",
            "infinitive": "wissen",
            "present": "weiß",
            "past": "wusste",
            "past_participle": "gewusst",
            "perfect_aux": "haben",
            "conjunctive2": "wüsste",
            "imperative": "weiß(wisse)",
            "ablaut": "uu"
        }
    ]
}
